{
  "totalMatches": 23,
  "wins": 16,
  "losses": 7,
  "totalWinRate": 0.696,
  "games": {
    "total": 134,
    "won": 86,
    "lost": 48,
    "gameRate": 0.642
  },
  "byPartner": {
    "motokura-kentaro": {
      "matches": {
        "total": 8,
        "wins": 6,
        "losses": 2,
        "winRate": 0.75
      },
      "games": {
        "total": 52,
        "won": 34,
        "lost": 18,
        "gameRate": 0.654
      }
    },
    "浪岡 菜々美": {
      "matches": {
        "total": 3,
        "wins": 2,
        "losses": 1,
        "winRate": 0.667
      },
      "games": {
        "total": 18,
        "won": 10,
        "lost": 8,
        "gameRate": 0.556
      }
    },
    "シングルス": {
      "matches": {
        "total": 8,
        "wins": 5,
        "losses": 3,
        "winRate": 0.625
      },
      "games": {
        "total": 36,
        "won": 25,
        "lost": 11,
        "gameRate": 0.694
      }
    },
    "nagae-koichi": {
      "matches": {
        "total": 4,
        "wins": 3,
        "losses": 1,
        "winRate": 0.75
      },
      "games": {
        "total": 28,
        "won": 17,
        "lost": 11,
        "gameRate": 0.607
      }
    }
  },
  "byYear": {
    "2025": {
      "matches": {
        "total": 19,
        "wins": 13,
        "losses": 6,
        "winRate": 0.684
      },
      "games": {
        "total": 106,
        "won": 69,
        "lost": 37,
        "gameRate": 0.651
      }
    },
    "2024": {
      "matches": {
        "total": 4,
        "wins": 3,
        "losses": 1,
        "winRate": 0.75
      },
      "games": {
        "total": 28,
        "won": 17,
        "lost": 11,
        "gameRate": 0.607
      }
    }
  },
  "latestMatch": {
    "tournament": "第79回 西日本ソフトテニス選手権大会",
    "date": "2025年7月12日(土)〜13日(日)",
    "location": "奈良県",
    "partner": "motokura-kentaro",
    "result": "4回戦敗退",
    "summary": "2025年に入り少し調子を落としている印象です。 しかし、全日本シングルス選手権では準々決勝まで進出し、実力を証明しました。",
    "link": ""
  }
}