[
{"id":1,"name":"中堀・森本（NTT西日本中国）","information":[{"lastName":"中堀","firstName":"成生","team":"NTT西日本中国","prefecture":"広島","playerId":null,"tempId":"中堀_成生_NTT西日本中国"},{"lastName":"森本","firstName":"英揮","team":"NTT西日本中国","prefecture":"広島","playerId":null,"tempId":"森本_英揮_NTT西日本中国"}],"category":"doubles"},
{"id":2,"name":"坂下・谷口（能美クラブ）","information":[{"lastName":"坂下","firstName":"桂介","team":"能美クラブ","prefecture":"石川","playerId":null,"tempId":"坂下_桂介_能美クラブ"},{"lastName":"谷口","firstName":"智彦","team":"加賀グリーンクラブ","prefecture":"石川","playerId":null,"tempId":"谷口_智彦_加賀グリーンクラブ"}],"category":"doubles"},
{"id":3,"name":"平野・福島（大田支部）","information":[{"lastName":"平野","firstName":"充","team":"大田支部","prefecture":"東京","playerId":null,"tempId":"平野_充_大田支部"},{"lastName":"福島","firstName":"悟","team":"深川テニス","prefecture":"東京","playerId":null,"tempId":"福島_悟_深川テニス"}],"category":"doubles"},
{"id":4,"name":"石橋・渡海（京都市役所）","information":[{"lastName":"石橋","firstName":"孝一","team":"京都市役所","prefecture":"京都","playerId":null,"tempId":"石橋_孝一_京都市役所"},{"lastName":"渡海","firstName":"聡","team":"和歌山県庁","prefecture":"和歌山","playerId":null,"tempId":"渡海_聡_和歌山県庁"}],"category":"doubles"},
{"id":5,"name":"宮里・山田（豊田自動織機）","information":[{"lastName":"宮里","firstName":"康成","team":"豊田自動織機","prefecture":"愛知","playerId":null,"tempId":"宮里_康成_豊田自動織機"},{"lastName":"山田","firstName":"栄作","team":"豊田自動織機","prefecture":"愛知","playerId":null,"tempId":"山田_栄作_豊田自動織機"}],"category":"doubles"},
{"id":6,"name":"長濱・石井（横浜市役所）","information":[{"lastName":"長濱","firstName":"悟史","team":"横浜市役所","prefecture":"神奈川","playerId":null,"tempId":"長濱_悟史_横浜市役所"},{"lastName":"石井","firstName":"俊洋","team":"須賀川サンデー","prefecture":"福島","playerId":null,"tempId":"石井_俊洋_須賀川サンデー"}],"category":"doubles"},
{"id":7,"name":"三好・福田（なかよしクラブ）","information":[{"lastName":"三好","firstName":"俊生","team":"なかよしクラブ","prefecture":"香川","playerId":null,"tempId":"三好_俊生_なかよしクラブ"},{"lastName":"福田","firstName":"晃大","team":"東大阪市協会","prefecture":"大阪","playerId":null,"tempId":"福田_晃大_東大阪市協会"}],"category":"doubles"},
{"id":8,"name":"杉山・豊田（ｽﾌｨｰﾀﾞﾃﾆｽｸﾗﾌﾞ）","information":[{"lastName":"杉山","firstName":"忍","team":"ｽﾌｨｰﾀﾞﾃﾆｽｸﾗﾌﾞ","prefecture":"岡山","playerId":null,"tempId":"杉山_忍_ｽﾌｨｰﾀﾞﾃﾆｽｸﾗﾌﾞ"},{"lastName":"豊田","firstName":"雅孝","team":"清須STC","prefecture":"愛知","playerId":null,"tempId":"豊田_雅孝_清須STC"}],"category":"doubles"},
{"id":9,"name":"大沼・黒河内（足立STC）","information":[{"lastName":"大沼","firstName":"亘","team":"足立STC","prefecture":"東京","playerId":null,"tempId":"大沼_亘_足立STC"},{"lastName":"黒河内","firstName":"武司","team":"伊那協会","prefecture":"長野","playerId":null,"tempId":"黒河内_武司_伊那協会"}],"category":"doubles"},
{"id":10,"name":"本山・福園（平野連盟）","information":[{"lastName":"本山","firstName":"雄介","team":"平野連盟","prefecture":"大阪","playerId":null,"tempId":"本山_雄介_平野連盟"},{"lastName":"福園","firstName":"勝","team":"平野連盟","prefecture":"大阪","playerId":null,"tempId":"福園_勝_平野連盟"}],"category":"doubles"},
{"id":11,"name":"藤木・星（わんぱくクラブ）","information":[{"lastName":"藤木","firstName":"聡","team":"わんぱくクラブ","prefecture":"北海道","playerId":null,"tempId":"藤木_聡_わんぱくクラブ"},{"lastName":"星","firstName":"雅哉","team":"ルーセント","prefecture":"千葉","playerId":null,"tempId":"星_雅哉_ルーセント"}],"category":"doubles"},
{"id":12,"name":"笠原・丸山（糸魚川クラブ）","information":[{"lastName":"笠原","firstName":"淳","team":"糸魚川クラブ","prefecture":"新潟","playerId":null,"tempId":"笠原_淳_糸魚川クラブ"},{"lastName":"丸山","firstName":"孝","team":"NSTC","prefecture":"新潟","playerId":null,"tempId":"丸山_孝_NSTC"}],"category":"doubles"},
{"id":13,"name":"嶋田・椎名（チームM's）","information":[{"lastName":"嶋田","firstName":"秀樹","team":"チームM's","prefecture":"埼玉","playerId":null,"tempId":"嶋田_秀樹_チームM's"},{"lastName":"椎名","firstName":"宏","team":"桜倶楽部","prefecture":"神奈川","playerId":null,"tempId":"椎名_宏_桜倶楽部"}],"category":"doubles"},
{"id":14,"name":"高橋・小森（春日井クラブ）","information":[{"lastName":"高橋","firstName":"寛","team":"春日井クラブ","prefecture":"愛知","playerId":null,"tempId":"高橋_寛_春日井クラブ"},{"lastName":"小森","firstName":"裕之","team":"千種クラブ","prefecture":"愛知","playerId":null,"tempId":"小森_裕之_千種クラブ"}],"category":"doubles"},
{"id":15,"name":"檜山・橋本（西東京市STA）","information":[{"lastName":"檜山","firstName":"武志","team":"西東京市STA","prefecture":"東京","playerId":null,"tempId":"檜山_武志_西東京市STA"},{"lastName":"橋本","firstName":"好貴","team":"たちばなクラブ","prefecture":"東京","playerId":null,"tempId":"橋本_好貴_たちばなクラブ"}],"category":"doubles"},
{"id":16,"name":"大和・吉川（パナソニックエレクトリックワークス）","information":[{"lastName":"大和","firstName":"賢治","team":"パナソニックエレクトリックワークス","prefecture":"大阪","playerId":null,"tempId":"大和_賢治_パナソニックエレクトリックワークス"},{"lastName":"吉川","firstName":"保孝","team":"パナソニックエレクトリックワークス","prefecture":"兵庫","playerId":null,"tempId":"吉川_保孝_パナソニックエレクトリックワークス"}],"category":"doubles"},
{"id":17,"name":"諏訪・佐々木（川口I.S.C）","information":[{"lastName":"諏訪","firstName":"徳男","team":"川口I.S.C","prefecture":"埼玉","playerId":null,"tempId":"諏訪_徳男_川口I.S.C"},{"lastName":"佐々木","firstName":"俊夫","team":"坂戸クラブ","prefecture":"埼玉","playerId":null,"tempId":"佐々木_俊夫_坂戸クラブ"}],"category":"doubles"},
{"id":18,"name":"宮村・川崎（野々市クラブ）","information":[{"lastName":"宮村","firstName":"憲治","team":"野々市クラブ","prefecture":"石川","playerId":null,"tempId":"宮村_憲治_野々市クラブ"},{"lastName":"川崎","firstName":"優","team":"能登町役場","prefecture":"石川","playerId":null,"tempId":"川崎_優_能登町役場"}],"category":"doubles"},
{"id":19,"name":"中島・平井（浜松市役所）","information":[{"lastName":"中島","firstName":"通晴","team":"浜松市役所","prefecture":"静岡","playerId":null,"tempId":"中島_通晴_浜松市役所"},{"lastName":"平井","firstName":"勝己","team":"デンソー","prefecture":"愛知","playerId":null,"tempId":"平井_勝己_デンソー"}],"category":"doubles"},
{"id":20,"name":"吉末・小宮（山口クラブ）","information":[{"lastName":"吉末","firstName":"尚之","team":"山口クラブ","prefecture":"山口","playerId":null,"tempId":"吉末_尚之_山口クラブ"},{"lastName":"小宮","firstName":"剛","team":"山口教員クラブ","prefecture":"山口","playerId":null,"tempId":"小宮_剛_山口教員クラブ"}],"category":"doubles"},
{"id":21,"name":"矢口・南（若月組）","information":[{"lastName":"矢口","firstName":"成","team":"若月組","prefecture":"東京","playerId":null,"tempId":"矢口_成_若月組"},{"lastName":"南","firstName":"隆行","team":"八王子庭球クラブ","prefecture":"東京","playerId":null,"tempId":"南_隆行_八王子庭球クラブ"}],"category":"doubles"},
{"id":22,"name":"佐々木・岩渕（ＴＧクラブ）","information":[{"lastName":"佐々木","firstName":"聡","team":"ＴＧクラブ","prefecture":"宮城","playerId":null,"tempId":"佐々木_聡_ＴＧクラブ"},{"lastName":"岩渕","firstName":"隆","team":"ＴＧクラブ","prefecture":"宮城","playerId":null,"tempId":"岩渕_隆_ＴＧクラブ"}],"category":"doubles"},
{"id":23,"name":"横山・松下（武生球友会）","information":[{"lastName":"横山","firstName":"幸夫","team":"武生球友会","prefecture":"福井","playerId":null,"tempId":"横山_幸夫_武生球友会"},{"lastName":"松下","firstName":"貴志","team":"EAST","prefecture":"福井","playerId":null,"tempId":"松下_貴志_EAST"}],"category":"doubles"},
{"id":24,"name":"鈴木・福地（日立はくあ）","information":[{"lastName":"鈴木","firstName":"聡","team":"日立はくあ","prefecture":"茨城","playerId":null,"tempId":"鈴木_聡_日立はくあ"},{"lastName":"福地","firstName":"智幸","team":"日立はくあ","prefecture":"茨城","playerId":null,"tempId":"福地_智幸_日立はくあ"}],"category":"doubles"},
{"id":25,"name":"榊原・橋本（兼六クラブ）","information":[{"lastName":"榊原","firstName":"雄司","team":"兼六クラブ","prefecture":"石川","playerId":null,"tempId":"榊原_雄司_兼六クラブ"},{"lastName":"橋本","firstName":"裕司","team":"守山クラブ","prefecture":"愛知","playerId":null,"tempId":"橋本_裕司_守山クラブ"}],"category":"doubles"},
{"id":26,"name":"佐竹・寺井（維吹）","information":[{"lastName":"佐竹","firstName":"康一","team":"維吹","prefecture":"和歌山","playerId":null,"tempId":"佐竹_康一_維吹"},{"lastName":"寺井","firstName":"誠","team":"維吹","prefecture":"和歌山","playerId":null,"tempId":"寺井_誠_維吹"}],"category":"doubles"},
{"id":27,"name":"平松・赤澤（せせらぎクラブ）","information":[{"lastName":"平松","firstName":"栄一","team":"せせらぎクラブ","prefecture":"神奈川","playerId":null,"tempId":"平松_栄一_せせらぎクラブ"},{"lastName":"赤澤","firstName":"稔","team":"JX金属倉見","prefecture":"神奈川","playerId":null,"tempId":"赤澤_稔_JX金属倉見"}],"category":"doubles"},
{"id":28,"name":"奥山・森宗（ENEOS）","information":[{"lastName":"奥山","firstName":"浩史","team":"ENEOS","prefecture":"岡山","playerId":null,"tempId":"奥山_浩史_ENEOS"},{"lastName":"森宗","firstName":"浩慈","team":"プロシード","prefecture":"岡山","playerId":null,"tempId":"森宗_浩慈_プロシード"}],"category":"doubles"},
{"id":29,"name":"加古・高久（オールブラザー）","information":[{"lastName":"加古","firstName":"武良","team":"オールブラザー","prefecture":"愛知","playerId":null,"tempId":"加古_武良_オールブラザー"},{"lastName":"高久","firstName":"薫","team":"三菱電機","prefecture":"愛知","playerId":null,"tempId":"高久_薫_三菱電機"}],"category":"doubles"},
{"id":30,"name":"河口・上田（練馬ソフト）","information":[{"lastName":"河口","firstName":"琢哉","team":"練馬ソフト","prefecture":"東京","playerId":null,"tempId":"河口_琢哉_練馬ソフト"},{"lastName":"上田","firstName":"大介","team":"練馬ソフト","prefecture":"東京","playerId":null,"tempId":"上田_大介_練馬ソフト"}],"category":"doubles"},
{"id":31,"name":"伊藤・三角（横浜ドリームズ）","information":[{"lastName":"伊藤","firstName":"浩二郎","team":"横浜ドリームズ","prefecture":"神奈川","playerId":null,"tempId":"伊藤_浩二郎_横浜ドリームズ"},{"lastName":"三角","firstName":"浩二","team":"横浜ドリームズ","prefecture":"神奈川","playerId":null,"tempId":"三角_浩二_横浜ドリームズ"}],"category":"doubles"},
{"id":32,"name":"河村・深草（YKK）","information":[{"lastName":"河村","firstName":"浩志","team":"YKK","prefecture":"富山","playerId":null,"tempId":"河村_浩志_YKK"},{"lastName":"深草","firstName":"博之","team":"YKK","prefecture":"富山","playerId":null,"tempId":"深草_博之_YKK"}],"category":"doubles"},
{"id":33,"name":"二宮・梶井（所沢テニスクラブ）","information":[{"lastName":"二宮","firstName":"大輔","team":"所沢テニスクラブ","prefecture":"埼玉","playerId":null,"tempId":"二宮_大輔_所沢テニスクラブ"},{"lastName":"梶井","firstName":"寛史","team":"所沢テニスクラブ","prefecture":"埼玉","playerId":null,"tempId":"梶井_寛史_所沢テニスクラブ"}],"category":"doubles"},
{"id":34,"name":"山田・田中（青葉クラブ）","information":[{"lastName":"山田","firstName":"丈生","team":"青葉クラブ","prefecture":"和歌山","playerId":null,"tempId":"山田_丈生_青葉クラブ"},{"lastName":"田中","firstName":"睦雄","team":"大阪府タフマンズ","prefecture":"大阪","playerId":null,"tempId":"田中_睦雄_大阪府タフマンズ"}],"category":"doubles"},
{"id":35,"name":"小笠原・清水（小金原クラブ）","information":[{"lastName":"小笠原","firstName":"敬之","team":"小金原クラブ","prefecture":"千葉","playerId":null,"tempId":"小笠原_敬之_小金原クラブ"},{"lastName":"清水","firstName":"賢二","team":"松戸市役所","prefecture":"千葉","playerId":null,"tempId":"清水_賢二_松戸市役所"}],"category":"doubles"},
{"id":36,"name":"山本・佐藤（日本まんなか倶楽部）","information":[{"lastName":"山本","firstName":"道彦","team":"日本まんなか倶楽部","prefecture":"滋賀","playerId":null,"tempId":"山本_道彦_日本まんなか倶楽部"},{"lastName":"佐藤","firstName":"正秀","team":"松葉クラブ","prefecture":"愛知","playerId":null,"tempId":"佐藤_正秀_松葉クラブ"}],"category":"doubles"},
{"id":37,"name":"櫻井・櫻井（かほくクラブ）","information":[{"lastName":"櫻井","firstName":"孝徳","team":"かほくクラブ","prefecture":"石川","playerId":null,"tempId":"櫻井_孝徳_かほくクラブ"},{"lastName":"櫻井","firstName":"敏久","team":"かほくクラブ","prefecture":"石川","playerId":null,"tempId":"櫻井_敏久_かほくクラブ"}],"category":"doubles"},
{"id":38,"name":"吉竹・小泉（城陽クラブ）","information":[{"lastName":"吉竹","firstName":"良泰","team":"城陽クラブ","prefecture":"京都","playerId":null,"tempId":"吉竹_良泰_城陽クラブ"},{"lastName":"小泉","firstName":"雄史","team":"橿原クラブ","prefecture":"奈良","playerId":null,"tempId":"小泉_雄史_橿原クラブ"}],"category":"doubles"},
{"id":39,"name":"井川・木原（岐阜しらさぎクラブ）","information":[{"lastName":"井川","firstName":"智詞","team":"岐阜しらさぎクラブ","prefecture":"岐阜","playerId":null,"tempId":"井川_智詞_岐阜しらさぎクラブ"},{"lastName":"木原","firstName":"寛之","team":"Freedomstc","prefecture":"岐阜","playerId":null,"tempId":"木原_寛之_Freedomstc"}],"category":"doubles"},
{"id":40,"name":"高島・岡崎（世田谷テニス）","information":[{"lastName":"高島","firstName":"務","team":"世田谷テニス","prefecture":"東京","playerId":null,"tempId":"高島_務_世田谷テニス"},{"lastName":"岡崎","firstName":"孝俊","team":"おおなん福祉会","prefecture":"島根","playerId":null,"tempId":"岡崎_孝俊_おおなん福祉会"}],"category":"doubles"},
{"id":41,"name":"岩城・小澤（東大阪市協会）","information":[{"lastName":"岩城","firstName":"靖彦","team":"東大阪市協会","prefecture":"大阪","playerId":null,"tempId":"岩城_靖彦_東大阪市協会"},{"lastName":"小澤","firstName":"隆浩","team":"たちばなクラブ","prefecture":"東京","playerId":null,"tempId":"小澤_隆浩_たちばなクラブ"}],"category":"doubles"},
{"id":42,"name":"櫻井・須田（城畔クラブ）","information":[{"lastName":"櫻井","firstName":"昇","team":"城畔クラブ","prefecture":"山形","playerId":null,"tempId":"櫻井_昇_城畔クラブ"},{"lastName":"須田","firstName":"一成","team":"V-max","prefecture":"山形","playerId":null,"tempId":"須田_一成_V-max"}],"category":"doubles"},
{"id":43,"name":"村谷・木津（日本製鉄大分）","information":[{"lastName":"村谷","firstName":"直喜","team":"日本製鉄大分","prefecture":"大分","playerId":null,"tempId":"村谷_直喜_日本製鉄大分"},{"lastName":"木津","firstName":"大幸","team":"ＳＢカワスミ","prefecture":"大分","playerId":null,"tempId":"木津_大幸_ＳＢカワスミ"}],"category":"doubles"},
{"id":44,"name":"横山・加藤（中部電力愛知）","information":[{"lastName":"横山","firstName":"晴生","team":"中部電力愛知","prefecture":"愛知","playerId":null,"tempId":"横山_晴生_中部電力愛知"},{"lastName":"加藤","firstName":"真澄","team":"中部電力愛知","prefecture":"愛知","playerId":null,"tempId":"加藤_真澄_中部電力愛知"}],"category":"doubles"},
{"id":45,"name":"大森・新田（中能登町STA）","information":[{"lastName":"大森","firstName":"幸誠","team":"中能登町STA","prefecture":"石川","playerId":null,"tempId":"大森_幸誠_中能登町STA"},{"lastName":"新田","firstName":"充","team":"野々市クラブ","prefecture":"石川","playerId":null,"tempId":"新田_充_野々市クラブ"}],"category":"doubles"},
{"id":46,"name":"植野・松田（稲門クラブ）","information":[{"lastName":"植野","firstName":"雅晶","team":"稲門クラブ","prefecture":"東京","playerId":null,"tempId":"植野_雅晶_稲門クラブ"},{"lastName":"松田","firstName":"孔司","team":"加古川クラブ","prefecture":"兵庫","playerId":null,"tempId":"松田_孔司_加古川クラブ"}],"category":"doubles"},
{"id":47,"name":"宇野・荻原（CAREOTH）","information":[{"lastName":"宇野","firstName":"鉄平","team":"CAREOTH","prefecture":"広島","playerId":null,"tempId":"宇野_鉄平_CAREOTH"},{"lastName":"荻原","firstName":"英司","team":"CAREOTH","prefecture":"広島","playerId":null,"tempId":"荻原_英司_CAREOTH"}],"category":"doubles"},
{"id":48,"name":"石丸・宇津木（せせらぎクラブ）","information":[{"lastName":"石丸","firstName":"茂樹","team":"せせらぎクラブ","prefecture":"神奈川","playerId":null,"tempId":"石丸_茂樹_せせらぎクラブ"},{"lastName":"宇津木","firstName":"智","team":"せせらぎクラブ","prefecture":"神奈川","playerId":null,"tempId":"宇津木_智_せせらぎクラブ"}],"category":"doubles"},
{"id":49,"name":"河野・豊嶋（みのわ協会）","information":[{"lastName":"河野","firstName":"公明","team":"みのわ協会","prefecture":"長野","playerId":null,"tempId":"河野_公明_みのわ協会"},{"lastName":"豊嶋","firstName":"篤志","team":"交友クラブ","prefecture":"新潟","playerId":null,"tempId":"豊嶋_篤志_交友クラブ"}],"category":"doubles"},
{"id":50,"name":"新田・横石（徳島市役所）","information":[{"lastName":"新田","firstName":"貴徳","team":"徳島市役所","prefecture":"徳島","playerId":null,"tempId":"新田_貴徳_徳島市役所"},{"lastName":"横石","firstName":"智","team":"大神子病院","prefecture":"徳島","playerId":null,"tempId":"横石_智_大神子病院"}],"category":"doubles"},
{"id":51,"name":"小野林・山西（ＵＢＥ堺工場）","information":[{"lastName":"小野林","firstName":"一彦","team":"ＵＢＥ堺工場","prefecture":"大阪","playerId":null,"tempId":"小野林_一彦_ＵＢＥ堺工場"},{"lastName":"山西","firstName":"浩之","team":"大阪狭山クラブ","prefecture":"大阪","playerId":null,"tempId":"山西_浩之_大阪狭山クラブ"}],"category":"doubles"},
{"id":52,"name":"中村・中村（上尾S.T.C）","information":[{"lastName":"中村","firstName":"雅司","team":"上尾S.T.C","prefecture":"埼玉","playerId":null,"tempId":"中村_雅司_上尾S.T.C"},{"lastName":"中村","firstName":"雅己","team":"コマツ粟津工場","prefecture":"石川","playerId":null,"tempId":"中村_雅己_コマツ粟津工場"}],"category":"doubles"},
{"id":53,"name":"渡部・末吉（朝日STC）","information":[{"lastName":"渡部","firstName":"繁樹","team":"朝日STC","prefecture":"愛知","playerId":null,"tempId":"渡部_繁樹_朝日STC"},{"lastName":"末吉","firstName":"巌","team":"デンソー","prefecture":"愛知","playerId":null,"tempId":"末吉_巌_デンソー"}],"category":"doubles"},
{"id":54,"name":"古川・岩間（市川クラブ）","information":[{"lastName":"古川","firstName":"敦","team":"市川クラブ","prefecture":"千葉","playerId":null,"tempId":"古川_敦_市川クラブ"},{"lastName":"岩間","firstName":"諭","team":"市川クラブ","prefecture":"千葉","playerId":null,"tempId":"岩間_諭_市川クラブ"}],"category":"doubles"},
{"id":55,"name":"中島・正田（千種クラブ）","information":[{"lastName":"中島","firstName":"一彰","team":"千種クラブ","prefecture":"愛知","playerId":null,"tempId":"中島_一彰_千種クラブ"},{"lastName":"正田","firstName":"憲史","team":"燦燦会","prefecture":"岡山","playerId":null,"tempId":"正田_憲史_燦燦会"}],"category":"doubles"},
{"id":56,"name":"鈴木・川島（旭テニス）","information":[{"lastName":"鈴木","firstName":"司","team":"旭テニス","prefecture":"東京","playerId":null,"tempId":"鈴木_司_旭テニス"},{"lastName":"川島","firstName":"正人","team":"言問","prefecture":"東京","playerId":null,"tempId":"川島_正人_言問"}],"category":"doubles"},
{"id":57,"name":"金子・大関（宇治市役所）","information":[{"lastName":"金子","firstName":"敬","team":"宇治市役所","prefecture":"京都","playerId":null,"tempId":"金子_敬_宇治市役所"},{"lastName":"大関","firstName":"慎士","team":"丸亀市役所","prefecture":"香川","playerId":null,"tempId":"大関_慎士_丸亀市役所"}],"category":"doubles"},
{"id":58,"name":"長尾・宮島（横浜ドリームズ）","information":[{"lastName":"長尾","firstName":"淳史","team":"横浜ドリームズ","prefecture":"神奈川","playerId":null,"tempId":"長尾_淳史_横浜ドリームズ"},{"lastName":"宮島","firstName":"正好","team":"横浜ドリームズ","prefecture":"神奈川","playerId":null,"tempId":"宮島_正好_横浜ドリームズ"}],"category":"doubles"},
{"id":59,"name":"星野・津幡（盛岡研究会）","information":[{"lastName":"星野","firstName":"信裕","team":"盛岡研究会","prefecture":"岩手","playerId":null,"tempId":"星野_信裕_盛岡研究会"},{"lastName":"津幡","firstName":"憲幸","team":"金沢市役所","prefecture":"石川","playerId":null,"tempId":"津幡_憲幸_金沢市役所"}],"category":"doubles"},
{"id":60,"name":"藤谷・廣瀬（川越FTC）","information":[{"lastName":"藤谷","firstName":"光章","team":"川越FTC","prefecture":"埼玉","playerId":null,"tempId":"藤谷_光章_川越FTC"},{"lastName":"廣瀬","firstName":"栄太郎","team":"川越FTC","prefecture":"埼玉","playerId":null,"tempId":"廣瀬_栄太郎_川越FTC"}],"category":"doubles"},
{"id":61,"name":"北野・大津（堺連盟）","information":[{"lastName":"北野","firstName":"敏明","team":"堺連盟","prefecture":"大阪","playerId":null,"tempId":"北野_敏明_堺連盟"},{"lastName":"大津","firstName":"竜二","team":"東邦ガス","prefecture":"愛知","playerId":null,"tempId":"大津_竜二_東邦ガス"}],"category":"doubles"},
{"id":62,"name":"百々・前田（深川テニス）","information":[{"lastName":"百々","firstName":"生勢","team":"深川テニス","prefecture":"東京","playerId":null,"tempId":"百々_生勢_深川テニス"},{"lastName":"前田","firstName":"恭宏","team":"赤門クラブ","prefecture":"東京","playerId":null,"tempId":"前田_恭宏_赤門クラブ"}],"category":"doubles"},
{"id":63,"name":"清水・小坂（YKK）","information":[{"lastName":"清水","firstName":"弘之","team":"YKK","prefecture":"富山","playerId":null,"tempId":"清水_弘之_YKK"},{"lastName":"小坂","firstName":"晃祥","team":"YKK","prefecture":"富山","playerId":null,"tempId":"小坂_晃祥_YKK"}],"category":"doubles"},
{"id":64,"name":"石本・中川（呉STC）","information":[{"lastName":"石本","firstName":"修一","team":"呉STC","prefecture":"広島","playerId":null,"tempId":"石本_修一_呉STC"},{"lastName":"中川","firstName":"修司","team":"日本製鋼所","prefecture":"広島","playerId":null,"tempId":"中川_修司_日本製鋼所"}],"category":"doubles"},
{"id":65,"name":"川田・宗像（富士見市連盟）","information":[{"lastName":"川田","firstName":"大輔","team":"富士見市連盟","prefecture":"埼玉","playerId":null,"tempId":"川田_大輔_富士見市連盟"},{"lastName":"宗像","firstName":"篤史","team":"上福岡テニスクラブ","prefecture":"埼玉","playerId":null,"tempId":"宗像_篤史_上福岡テニスクラブ"}],"category":"doubles"},
{"id":66,"name":"大田・倉本（滋賀21クラブ）","information":[{"lastName":"大田","firstName":"真史","team":"滋賀21クラブ","prefecture":"滋賀","playerId":null,"tempId":"大田_真史_滋賀21クラブ"},{"lastName":"倉本","firstName":"和広","team":"滋賀21クラブ","prefecture":"滋賀","playerId":null,"tempId":"倉本_和広_滋賀21クラブ"}],"category":"doubles"},
{"id":67,"name":"豆崎・吉田（三木クラブ）","information":[{"lastName":"豆崎","firstName":"一樹","team":"三木クラブ","prefecture":"兵庫","playerId":null,"tempId":"豆崎_一樹_三木クラブ"},{"lastName":"吉田","firstName":"康照","team":"高槻クラブ","prefecture":"大阪","playerId":null,"tempId":"吉田_康照_高槻クラブ"}],"category":"doubles"},
{"id":68,"name":"荒川・松木田（日立はくあ）","information":[{"lastName":"荒川","firstName":"卓郎","team":"日立はくあ","prefecture":"茨城","playerId":null,"tempId":"荒川_卓郎_日立はくあ"},{"lastName":"松木田","firstName":"和明","team":"日立はくあ","prefecture":"茨城","playerId":null,"tempId":"松木田_和明_日立はくあ"}],"category":"doubles"},
{"id":69,"name":"山田・森（野々市クラブ）","information":[{"lastName":"山田","firstName":"豊","team":"野々市クラブ","prefecture":"石川","playerId":null,"tempId":"山田_豊_野々市クラブ"},{"lastName":"森","firstName":"崇","team":"かほくクラブ","prefecture":"石川","playerId":null,"tempId":"森_崇_かほくクラブ"}],"category":"doubles"},
{"id":70,"name":"宇佐美・早坂（ＦＵＪＩＹＡＭＡ）","information":[{"lastName":"宇佐美","firstName":"潤","team":"ＦＵＪＩＹＡＭＡ","prefecture":"静岡","playerId":null,"tempId":"宇佐美_潤_ＦＵＪＩＹＡＭＡ"},{"lastName":"早坂","firstName":"弘","team":"ウイナークラブ","prefecture":"宮城","playerId":null,"tempId":"早坂_弘_ウイナークラブ"}],"category":"doubles"},
{"id":71,"name":"水田・藤原（JFEスチール西日本倉敷）","information":[{"lastName":"水田","firstName":"佳邦","team":"JFEスチール西日本倉敷","prefecture":"岡山","playerId":null,"tempId":"水田_佳邦_JFEスチール西日本倉敷"},{"lastName":"藤原","firstName":"基弘","team":"JFEスチール西日本倉敷","prefecture":"岡山","playerId":null,"tempId":"藤原_基弘_JFEスチール西日本倉敷"}],"category":"doubles"},
{"id":72,"name":"豊田・廣畑（たちばなクラブ）","information":[{"lastName":"豊田","firstName":"健司","team":"たちばなクラブ","prefecture":"東京","playerId":null,"tempId":"豊田_健司_たちばなクラブ"},{"lastName":"廣畑","firstName":"聡","team":"たちばなクラブ","prefecture":"東京","playerId":null,"tempId":"廣畑_聡_たちばなクラブ"}],"category":"doubles"},
{"id":73,"name":"伊藤・谷（維吹）","information":[{"lastName":"伊藤","firstName":"啓司","team":"維吹","prefecture":"和歌山","playerId":null,"tempId":"伊藤_啓司_維吹"},{"lastName":"谷","firstName":"弘樹","team":"維吹","prefecture":"和歌山","playerId":null,"tempId":"谷_弘樹_維吹"}],"category":"doubles"},
{"id":74,"name":"前川・余頃（草加若葉会）","information":[{"lastName":"前川","firstName":"貴範","team":"草加若葉会","prefecture":"埼玉","playerId":null,"tempId":"前川_貴範_草加若葉会"},{"lastName":"余頃","firstName":"泰之","team":"草加若葉会","prefecture":"埼玉","playerId":null,"tempId":"余頃_泰之_草加若葉会"}],"category":"doubles"},
{"id":75,"name":"加古・大場（ウシダクラブ）","information":[{"lastName":"加古","firstName":"政宏","team":"ウシダクラブ","prefecture":"愛知","playerId":null,"tempId":"加古_政宏_ウシダクラブ"},{"lastName":"大場","firstName":"始","team":"A&US.T.C","prefecture":"愛知","playerId":null,"tempId":"大場_始_A&US.T.C"}],"category":"doubles"},
{"id":76,"name":"東根・中道（銀座蒼穹会）","information":[{"lastName":"東根","firstName":"正興","team":"銀座蒼穹会","prefecture":"東京","playerId":null,"tempId":"東根_正興_銀座蒼穹会"},{"lastName":"中道","firstName":"大輔","team":"銀座蒼穹会","prefecture":"東京","playerId":null,"tempId":"中道_大輔_銀座蒼穹会"}],"category":"doubles"},
{"id":77,"name":"武内・柴崎（マツダ）","information":[{"lastName":"武内","firstName":"哲也","team":"マツダ","prefecture":"広島","playerId":null,"tempId":"武内_哲也_マツダ"},{"lastName":"柴崎","firstName":"旭仁","team":"五日市クラブ","prefecture":"広島","playerId":null,"tempId":"柴崎_旭仁_五日市クラブ"}],"category":"doubles"},
{"id":78,"name":"小林・千葉（伊那協会）","information":[{"lastName":"小林","firstName":"秀敏","team":"伊那協会","prefecture":"長野","playerId":null,"tempId":"小林_秀敏_伊那協会"},{"lastName":"千葉","firstName":"晃","team":"伊那協会","prefecture":"長野","playerId":null,"tempId":"千葉_晃_伊那協会"}],"category":"doubles"},
{"id":79,"name":"太田・小林（JX金属倉見）","information":[{"lastName":"太田","firstName":"努","team":"JX金属倉見","prefecture":"神奈川","playerId":null,"tempId":"太田_努_JX金属倉見"},{"lastName":"小林","firstName":"宗","team":"ＪＯＨＮＮＹ’Ｓ","prefecture":"神奈川","playerId":null,"tempId":"小林_宗_ＪＯＨＮＮＹ’Ｓ"}],"category":"doubles"},
{"id":80,"name":"石森・朴（KEISPORTS）","information":[{"lastName":"石森","firstName":"慶哉","team":"KEISPORTS","prefecture":"宮城","playerId":null,"tempId":"石森_慶哉_KEISPORTS"},{"lastName":"朴","firstName":"相俊","team":"HIN-HIN","prefecture":"長野","playerId":null,"tempId":"朴_相俊_HIN-HIN"}],"category":"doubles"},
{"id":81,"name":"山元・小林（銀座蒼穹会）","information":[{"lastName":"山元","firstName":"康王","team":"銀座蒼穹会","prefecture":"東京","playerId":null,"tempId":"山元_康王_銀座蒼穹会"},{"lastName":"小林","firstName":"英之","team":"小金井テニス","prefecture":"東京","playerId":null,"tempId":"小林_英之_小金井テニス"}],"category":"doubles"},
{"id":82,"name":"森・間瀬（デンソー）","information":[{"lastName":"森","firstName":"寛之","team":"デンソー","prefecture":"愛知","playerId":null,"tempId":"森_寛之_デンソー"},{"lastName":"間瀬","firstName":"晃","team":"A&US.T.C","prefecture":"愛知","playerId":null,"tempId":"間瀬_晃_A&US.T.C"}],"category":"doubles"},
{"id":83,"name":"熊谷・櫻井（太田庭球クラブ）","information":[{"lastName":"熊谷","firstName":"幸司","team":"太田庭球クラブ","prefecture":"群馬","playerId":null,"tempId":"熊谷_幸司_太田庭球クラブ"},{"lastName":"櫻井","firstName":"春樹","team":"碓氷安中クラブ","prefecture":"群馬","playerId":null,"tempId":"櫻井_春樹_碓氷安中クラブ"}],"category":"doubles"},
{"id":84,"name":"谷・長田（野々市クラブ）","information":[{"lastName":"谷","firstName":"勝義","team":"野々市クラブ","prefecture":"石川","playerId":null,"tempId":"谷_勝義_野々市クラブ"},{"lastName":"長田","firstName":"正行","team":"金沢愛好会","prefecture":"石川","playerId":null,"tempId":"長田_正行_金沢愛好会"}],"category":"doubles"},
{"id":85,"name":"仁科・有本（ダンディズム）","information":[{"lastName":"仁科","firstName":"茂樹","team":"ダンディズム","prefecture":"岡山","playerId":null,"tempId":"仁科_茂樹_ダンディズム"},{"lastName":"有本","firstName":"好孝","team":"ダンディズム","prefecture":"岡山","playerId":null,"tempId":"有本_好孝_ダンディズム"}],"category":"doubles"},
{"id":86,"name":"大釜・山田（藤井寺市連盟）","information":[{"lastName":"大釜","firstName":"芳英","team":"藤井寺市連盟","prefecture":"大阪","playerId":null,"tempId":"大釜_芳英_藤井寺市連盟"},{"lastName":"山田","firstName":"博義","team":"豊田自動織機","prefecture":"愛知","playerId":null,"tempId":"山田_博義_豊田自動織機"}],"category":"doubles"},
{"id":87,"name":"縄田・吉國（宇部市役所）","information":[{"lastName":"縄田","firstName":"栄二","team":"宇部市役所","prefecture":"山口","playerId":null,"tempId":"縄田_栄二_宇部市役所"},{"lastName":"吉國","firstName":"公人","team":"山口教員クラブ","prefecture":"山口","playerId":null,"tempId":"吉國_公人_山口教員クラブ"}],"category":"doubles"},
{"id":88,"name":"今井・小川（魚沼クラブ）","information":[{"lastName":"今井","firstName":"紀明","team":"魚沼クラブ","prefecture":"新潟","playerId":null,"tempId":"今井_紀明_魚沼クラブ"},{"lastName":"小川","firstName":"裕之","team":"魚沼クラブ","prefecture":"新潟","playerId":null,"tempId":"小川_裕之_魚沼クラブ"}],"category":"doubles"},
{"id":89,"name":"久保・原田（教友クラブ）","information":[{"lastName":"久保","firstName":"雅秀","team":"教友クラブ","prefecture":"和歌山","playerId":null,"tempId":"久保_雅秀_教友クラブ"},{"lastName":"原田","firstName":"隆志","team":"NTT関西","prefecture":"大阪","playerId":null,"tempId":"原田_隆志_NTT関西"}],"category":"doubles"},
{"id":90,"name":"上村・前田（ミドウクラブ）","information":[{"lastName":"上村","firstName":"友和","team":"ミドウクラブ","prefecture":"東京","playerId":null,"tempId":"上村_友和_ミドウクラブ"},{"lastName":"前田","firstName":"勇","team":"BLUEGRASS","prefecture":"東京","playerId":null,"tempId":"前田_勇_BLUEGRASS"}],"category":"doubles"},
{"id":91,"name":"瀬戸・西澤（兼六クラブ）","information":[{"lastName":"瀬戸","firstName":"真一","team":"兼六クラブ","prefecture":"石川","playerId":null,"tempId":"瀬戸_真一_兼六クラブ"},{"lastName":"西澤","firstName":"文彦","team":"兼六クラブ","prefecture":"石川","playerId":null,"tempId":"西澤_文彦_兼六クラブ"}],"category":"doubles"},
{"id":92,"name":"田中・朝倉（日本信号）","information":[{"lastName":"田中","firstName":"守","team":"日本信号","prefecture":"埼玉","playerId":null,"tempId":"田中_守_日本信号"},{"lastName":"朝倉","firstName":"勝美","team":"札幌学院クラブ","prefecture":"北海道","playerId":null,"tempId":"朝倉_勝美_札幌学院クラブ"}],"category":"doubles"},
{"id":93,"name":"伊藤・塚原（せせらぎクラブ）","information":[{"lastName":"伊藤","firstName":"宗一郎","team":"せせらぎクラブ","prefecture":"神奈川","playerId":null,"tempId":"伊藤_宗一郎_せせらぎクラブ"},{"lastName":"塚原","firstName":"達也","team":"せせらぎクラブ","prefecture":"神奈川","playerId":null,"tempId":"塚原_達也_せせらぎクラブ"}],"category":"doubles"},
{"id":94,"name":"今村・石井（なかよしクラブ）","information":[{"lastName":"今村","firstName":"義美","team":"なかよしクラブ","prefecture":"香川","playerId":null,"tempId":"今村_義美_なかよしクラブ"},{"lastName":"石井","firstName":"靖浩","team":"ENEOS","prefecture":"岡山","playerId":null,"tempId":"石井_靖浩_ENEOS"}],"category":"doubles"},
{"id":95,"name":"前澤・定政（福井県庁）","information":[{"lastName":"前澤","firstName":"陽平","team":"福井県庁","prefecture":"福井","playerId":null,"tempId":"前澤_陽平_福井県庁"},{"lastName":"定政","firstName":"弘憲","team":"武生球友会","prefecture":"福井","playerId":null,"tempId":"定政_弘憲_武生球友会"}],"category":"doubles"},
{"id":96,"name":"小久保・阿多（一心フランダース）","information":[{"lastName":"小久保","firstName":"義隆","team":"一心フランダース","prefecture":"東京","playerId":null,"tempId":"小久保_義隆_一心フランダース"},{"lastName":"阿多","firstName":"弘伸","team":"裾野クラブ","prefecture":"静岡","playerId":null,"tempId":"阿多_弘伸_裾野クラブ"}],"category":"doubles"},
{"id":97,"name":"須山・玉川（八尾市協会）","information":[{"lastName":"須山","firstName":"恒旨","team":"八尾市協会","prefecture":"大阪","playerId":null,"tempId":"須山_恒旨_八尾市協会"},{"lastName":"玉川","firstName":"功","team":"東大阪市協会","prefecture":"大阪","playerId":null,"tempId":"玉川_功_東大阪市協会"}],"category":"doubles"},
{"id":98,"name":"冨田・小山（桜クラブ）","information":[{"lastName":"冨田","firstName":"泰志","team":"桜クラブ","prefecture":"愛知","playerId":null,"tempId":"冨田_泰志_桜クラブ"},{"lastName":"小山","firstName":"慎二","team":"小平クラブ","prefecture":"東京","playerId":null,"tempId":"小山_慎二_小平クラブ"}],"category":"doubles"},
{"id":99,"name":"東・國場（名護スポーツ）","information":[{"lastName":"東","firstName":"竜一郎","team":"名護スポーツ","prefecture":"沖縄","playerId":null,"tempId":"東_竜一郎_名護スポーツ"},{"lastName":"國場","firstName":"幸野","team":"名護スポーツ","prefecture":"沖縄","playerId":null,"tempId":"國場_幸野_名護スポーツ"}],"category":"doubles"},
{"id":100,"name":"岡部・坂口（日亜化学工業）","information":[{"lastName":"岡部","firstName":"徳太郎","team":"日亜化学工業","prefecture":"徳島","playerId":null,"tempId":"岡部_徳太郎_日亜化学工業"},{"lastName":"坂口","firstName":"大","team":"市尼OBクラブ","prefecture":"兵庫","playerId":null,"tempId":"坂口_大_市尼OBクラブ"}],"category":"doubles"},
{"id":101,"name":"石井・藤田（大田支部）","information":[{"lastName":"石井","firstName":"一匡","team":"大田支部","prefecture":"東京","playerId":null,"tempId":"石井_一匡_大田支部"},{"lastName":"藤田","firstName":"義嗣","team":"稲門クラブ","prefecture":"東京","playerId":null,"tempId":"藤田_義嗣_稲門クラブ"}],"category":"doubles"},
{"id":102,"name":"中・道端（コマツ粟津工場）","information":[{"lastName":"中","firstName":"卓也","team":"コマツ粟津工場","prefecture":"石川","playerId":null,"tempId":"中_卓也_コマツ粟津工場"},{"lastName":"道端","firstName":"秀秋","team":"北陸電力石川","prefecture":"石川","playerId":null,"tempId":"道端_秀秋_北陸電力石川"}],"category":"doubles"},
{"id":103,"name":"山田・宮野（浦和あづまクラブ）","information":[{"lastName":"山田","firstName":"真人","team":"浦和あづまクラブ","prefecture":"埼玉","playerId":null,"tempId":"山田_真人_浦和あづまクラブ"},{"lastName":"宮野","firstName":"薫","team":"Nextテニスクラブ","prefecture":"埼玉","playerId":null,"tempId":"宮野_薫_Nextテニスクラブ"}],"category":"doubles"},
{"id":104,"name":"霜田・下柳（小島プレス）","information":[{"lastName":"霜田","firstName":"祐介","team":"小島プレス","prefecture":"愛知","playerId":null,"tempId":"霜田_祐介_小島プレス"},{"lastName":"下柳","firstName":"隆幸","team":"朝日STC","prefecture":"愛知","playerId":null,"tempId":"下柳_隆幸_朝日STC"}],"category":"doubles"},
{"id":105,"name":"高岡・茅嶋（横浜ドリームズ）","information":[{"lastName":"高岡","firstName":"竜太","team":"横浜ドリームズ","prefecture":"神奈川","playerId":null,"tempId":"高岡_竜太_横浜ドリームズ"},{"lastName":"茅嶋","firstName":"充","team":"東陵クラブ","prefecture":"神奈川","playerId":null,"tempId":"茅嶋_充_東陵クラブ"}],"category":"doubles"},
{"id":106,"name":"岩永・奥村（NTT西日本中国）","information":[{"lastName":"岩永","firstName":"淳","team":"NTT西日本中国","prefecture":"広島","playerId":null,"tempId":"岩永_淳_NTT西日本中国"},{"lastName":"奥村","firstName":"陸矢","team":"綾小路クラブ","prefecture":"福岡","playerId":null,"tempId":"奥村_陸矢_綾小路クラブ"}],"category":"doubles"}
]